{
  "ALIMENTOS E BEBIDAS": {
    "TAGS": [
      "ATIVAÇÃO", "BARMAN", "CATERING", "CHEF", "COPEIRO", "FINGER FOOD", 
      "FOOD TRUCKS", "GARÇOM", "GLUTEN FREE", "LOGISTICA", "SOMMELIER", 
      "UTENSILIOS", "VEGAN", "CHURRASQUEIRO", "COFFEE BREAK", "EQUIPE DE SERVIÇO", "LIMPEZA"
    ]
  },
  "ATRAÇÕES": {
    "TAGS": [
      "ATOR", "CERIMONIALISTA", "DJ", "INFLUENCIADORES", "PALESTRANTE", "TEAM BUILDING"
    ]
  },
  "BRINDES": {
    "TAGS": [
      "BRINDES", "BRINDES SUSTENTÁVEIS", "BRINDES TECNOLÓGICOS", "EMBALAGENS CRIATIVAS", 
      "GIFT CARDS", "PLACAS", "TROFÉUS", "VESTUARIO", "VOUCHERS", "MIMOS PARA EVENTOS"
    ]
  },
  "CENOGRAFIA": {
    "TAGS": [
      "BACKDROP", "CARREGADORES", "DESIGN 3D", "DESIGN DE PALCO", "EVENTOS CORPORATIVOS", 
      "MATERIAIS SUSTENTÁVEIS", "PAINEIS", "PINTURA", "PROJEÇÃO MAPEADA", "STANDS"
    ]
  },
  "COMUNICAÇÃO": {
    "TAGS": [
      "ASSESSORIA DE IMPRENSA", "CRIAÇÃO", "DIRETOR DE ARTE", "DIRETOR TECNICO", "IDENTIDADE VISUAL", 
      "INFLUENCIADORES", "PLANNER", "PRESS KITS", "REDATOR", "ROTEIRISTA", "SOCIAL MIDIA"
    ]
  },
  "CONTEUDO": {
    "TAGS": [
      "APRESENTAÇÕES", "COBERTURA JORNALISTICA", "EDIÇÃO DE VÍDEO", "NARRAÇÃO", "PPT", 
      "ROTEIROS", "TRANSMISSÃO AO VIVO"
    ]
  },
  "DECORAÇÃO": {
    "TAGS": [
      "ARRANJOS FLORAIS", "ARRANJOS TEMATICOS", "BALÕES", "BRANDING", "DECORAÇÃO SUSTENTAVEL", 
      "ILUMINAÇÃO", "MOBILIARIO", "TAPEÇARIA"
    ]
  },
  "EQUIPAMENTOS": {
    "TAGS": [
      "AR CONDICIONADO", "EQUIPAMENTOS AUDIO VISUAIS", "EQUIPAMENTOS PARA PALCO", "GERADORES", 
      "ILUMINAÇÃO", "INTERNET", "PAINEIS INTERATIVOS", "PLATAFORMAS ELEVATÓRIAS", "SONORIZAÇÃO", 
      "TELÕES LED"
    ]
  },
  "ESPACES PARA EVENTOS": {
    "TAGS": [
      "APARTAMENTO", "CASA", "CASA DE CONDOMINIO", "CENTRO DE CONVENÇÕES", "ESPAÇO AO AR LIVRE", 
      "FAZENDA", "GALPÕES", "HOTEIS COM ESPAÇO DE EVENTOS", "MUSEUS", "RESTAURANTES", 
      "SALÕES DE LUXO", "TEATROS", "VISTA PANORAMICA", "ONIBUS EXECUTIVO", "CO WORKING"
    ]
  },
  "FOTO / VÍDEO": {
    "TAGS": [
      "ALBUM DIGITAL", "COBERTURA 360º", "DRONE AEREO", "EDIÇÃO PROFISSIONAL", "FOTOGRAFIA CORPORATIVA", 
      "ILUMINAÇÃO PARA FOTOGRAFIA", "MAKING OF", "TRANSMISSÃO AO VIVO", "VIDEO INSTITUCIONAL"
    ]
  },
  "HOSPEDAGEM": {
    "TAGS": [
      "ESTACIONAMENTO", "HOTEL 3 ESTRELAS", "HOTEL 4 ESTRELAS", "HOTEL 5 ESTRELAS", 
      "HOTEIS", "HOTEIS COM ESPAÇOS PARA EVENTOS", "POUSADAS", "PISCINA", "SERVIÇO DE QUARTO", 
      "SERVIÇO DE QUARTO 24HS", "SUITES EXECUTIVAS", "VALLET", "HOSPEDAGEM VIP"
    ]
  },
  "LICENÇAS E TAXAS": {
    "TAGS": [
      "ALVARÁS MUNICIPAIS", "ARTs", "CERTIFICADO DE BOMBEIROS", "ECAD", "LICENÇAS", "PERMISSÕES", 
      "REGISTROS", "SEGUROS"
    ]
  },
  "MONTADORAS": {
    "TAGS": [
      "ARMAZENAGEM TEMPORÁRIA", "CARPINTARIA", "EPI", "INSTALAÇÕES", "LOGÍSTICA", "MONTAGEM DE ESTRUTURAS", 
      "PINTURA", "SSPENSÃO DE EQUIPAMENTOS"
    ]
  },
  "RH - PROFISSIONAIS DE EVENTOS": {
    "TAGS": [
      "ASSISTENTE DE PALCO", "BARMAN", "BOMBEIRO", "CARREGADORES", "COORDENADOR LOGÍSTICA", 
      "COPEIRO", "DIRETOR TECNICO", "ENFERMEIRO", "GARÇOM", "INFLUENCIADORES", "LIMPEZA", 
      "MANOBRISTA", "MEDICO", "MODELOS", "PALESTRANTE", "PRODUTOR ARTISTICO", "PRODUTOR AUDIO VISUAL", 
      "PRODUTOR FREELANCER", "PRODUTOR MASTER", "PRODUTOR MULTILINGUE", "PRODUTOR TECNICO", 
      "PRODUTOR APOIO", "PRODUTOR AUDIO VISUAL", "PRODUTOR LOGÍSTICO", "PRODUTOR MULTILINGUE", 
      "PROFISSIONAIS BILINGUES", "RECEPCIONISTA", "SEGURANÇA", "TECNICO AUDIO VISUAL", "TECNICO TI", 
      "TRADUTOR"
    ]
  },
  "SEGURO": {
    "TAGS": [
      "AVALIAÇÃO DE RISCOS", "COBERTURA DE CLIMA", "COBERTURA DE DANOS MATERIAIS", "COBERTURA DE TRANSPORTE DE CARGAS",
      "COBERTURA SAÚDE", "RESPONSABILIDADE CIVIL", "SEGURO DE EQUIPAMENTOS", "SEGURO VIDA", 
      "SEGURO PARA ARTISTAS", "SEGURO TRANSPORTE"
    ]
  },
  "SERVIÇOS DE APOIO": {
    "TAGS": [
      "AMBULANCIA", "BRIGADISTA", "EPI", "EXTINTORES", "GESTÃO DE RESIDUOS", "LIMPEZA", 
      "PONTOS DE RECARGA (CELULAR)", "RECEPCÃO", "RECREAÇÃO", "SINALIZAÇÃO", "ENGENHARIA DE TRAFEGO", 
      "GUIA TURISTICO"
    ]
  },
  "TRANSPORTE": {
    "TAGS": [
      "BLINDADOS", "CARRO EXECUTIVO", "COORDENADOR LOGÍSTICA", "FROTA DE LUXO", "MOTOBOY", 
      "MOTORISTAS BILINGUES", "ONIBUS EXECUTIVO", "ROTEIRIZAÇÃO", "SEGURO PARA PASSAGEIROS", 
      "TRANSPORTE AEREO", "TRANSPORTE FLUVIAL", "TRANSPORTE NAVAL", "TRANSFER", "VEICULOS EXECUTIVOS", 
      "VAN EXECUTIVA"
    ]
  },
  "TECNOLOGIA": {
    "TAGS": [
      "APLICATIVOS", "CREDENCIAMENTO", "DRONES", "INTERNET", "PAINEIS INTERATIVOS", 
      "PLATAFORMAS DE STREAMING", "PROJECOES 3D", "REALIDADE AUMENTADA", "SISTEMAS DE VOTAÇÃO EM TEMPO REAL", 
      "CHECK IN DIGITAL"
    ]
  },
  "TRADUÇÃO": {
    "TAGS": [
      "CABINES DE TRADUÇÃO", "EQUIPAMENTOS DE AUDIO PARA TRADUÇÃO", "INTERPRETES SIMUNTANEOS", 
      "LEGENDAS EM TEMPO REAL", "MULTILINGUES PARA RECEPÇÃO", "PROFISSIONAIS BILINGUES", "SERVIÇOS EM LIBRAS", 
      "TRADUÇÃO DE DOCUMENTOS", "TRADUÇÃO PARA APPS", "TRADUÇÃO TECNICA", "TRADUTORES JURIDICOS"
    ]
  }
}
